[
  {
    "inputs": [
      { "internalType": "address", "name": "priceFeed", "type": "address" },
      {
        "internalType": "address",
        "name": "vrfCoordinatorV2",
        "type": "address"
      },
      { "internalType": "uint64", "name": "subscriptionId", "type": "uint64" },
      { "internalType": "bytes32", "name": "gasLane", "type": "bytes32" },
      {
        "internalType": "uint32",
        "name": "callbackGasLimit",
        "type": "uint32"
      },
      { "internalType": "address", "name": "hub", "type": "address" },
      { "internalType": "address", "name": "moduleGlobals", "type": "address" },
      {
        "internalType": "address",
        "name": "poolAddressesProvider",
        "type": "address"
      },
      {
        "internalType": "address",
        "name": "wmaticTokenAddress",
        "type": "address"
      },
      {
        "internalType": "address",
        "name": "awmaticTokenAddress",
        "type": "address"
      }
    ],
    "stateMutability": "nonpayable",
    "type": "constructor"
  },
  { "inputs": [], "name": "Flowmi__CantFlowmiFollowYourself", "type": "error" },
  { "inputs": [], "name": "Flowmi__SendMoreToEnterFlowmi", "type": "error" },
  { "inputs": [], "name": "Flowmi__TransferFailed", "type": "error" },
  { "inputs": [], "name": "InitParamsInvalid", "type": "error" },
  { "inputs": [], "name": "NotHub", "type": "error" },
  {
    "inputs": [
      { "internalType": "address", "name": "have", "type": "address" },
      { "internalType": "address", "name": "want", "type": "address" }
    ],
    "name": "OnlyCoordinatorCanFulfill",
    "type": "error"
  },
  {
    "anonymous": false,
    "inputs": [
      {
        "indexed": true,
        "internalType": "address",
        "name": "userAddr",
        "type": "address"
      },
      {
        "indexed": false,
        "internalType": "uint256",
        "name": "amount",
        "type": "uint256"
      }
    ],
    "name": "Deposit",
    "type": "event"
  },
  {
    "anonymous": false,
    "inputs": [
      {
        "indexed": false,
        "internalType": "uint256",
        "name": "requestId",
        "type": "uint256"
      },
      {
        "indexed": false,
        "internalType": "uint256[]",
        "name": "randomWords",
        "type": "uint256[]"
      }
    ],
    "name": "RequestFulfilled",
    "type": "event"
  },
  {
    "anonymous": false,
    "inputs": [
      {
        "indexed": false,
        "internalType": "uint256",
        "name": "requestId",
        "type": "uint256"
      },
      {
        "indexed": false,
        "internalType": "uint32",
        "name": "numWords",
        "type": "uint32"
      }
    ],
    "name": "RequestSent",
    "type": "event"
  },
  {
    "anonymous": false,
    "inputs": [
      {
        "indexed": true,
        "internalType": "address",
        "name": "userAddr",
        "type": "address"
      },
      {
        "indexed": false,
        "internalType": "uint256",
        "name": "amount",
        "type": "uint256"
      }
    ],
    "name": "Withdraw",
    "type": "event"
  },
  { "stateMutability": "payable", "type": "fallback" },
  {
    "inputs": [],
    "name": "HUB",
    "outputs": [{ "internalType": "address", "name": "", "type": "address" }],
    "stateMutability": "view",
    "type": "function"
  },
  {
    "inputs": [],
    "name": "MODULE_GLOBALS",
    "outputs": [{ "internalType": "address", "name": "", "type": "address" }],
    "stateMutability": "view",
    "type": "function"
  },
  {
    "inputs": [{ "internalType": "address", "name": "", "type": "address" }],
    "name": "balances",
    "outputs": [{ "internalType": "uint256", "name": "", "type": "uint256" }],
    "stateMutability": "view",
    "type": "function"
  },
  {
    "inputs": [
      { "internalType": "uint256", "name": "profileId", "type": "uint256" },
      { "internalType": "address", "name": "from", "type": "address" },
      { "internalType": "address", "name": "to", "type": "address" },
      {
        "internalType": "uint256",
        "name": "followNFTTokenId",
        "type": "uint256"
      }
    ],
    "name": "followModuleTransferHook",
    "outputs": [],
    "stateMutability": "nonpayable",
    "type": "function"
  },
  {
    "inputs": [],
    "name": "getBalance",
    "outputs": [{ "internalType": "uint256", "name": "", "type": "uint256" }],
    "stateMutability": "view",
    "type": "function"
  },
  {
    "inputs": [],
    "name": "getFlowmiCost",
    "outputs": [{ "internalType": "uint256", "name": "", "type": "uint256" }],
    "stateMutability": "pure",
    "type": "function"
  },
  {
    "inputs": [],
    "name": "getFlowmiState",
    "outputs": [{ "internalType": "uint256", "name": "", "type": "uint256" }],
    "stateMutability": "pure",
    "type": "function"
  },
  {
    "inputs": [
      { "internalType": "address", "name": "_profileid", "type": "address" },
      { "internalType": "uint256", "name": "_index", "type": "uint256" }
    ],
    "name": "getFollowerOfIndex",
    "outputs": [{ "internalType": "address", "name": "", "type": "address" }],
    "stateMutability": "view",
    "type": "function"
  },
  {
    "inputs": [
      { "internalType": "address", "name": "_profileid", "type": "address" }
    ],
    "name": "getFollowsToRaffle",
    "outputs": [{ "internalType": "uint256", "name": "", "type": "uint256" }],
    "stateMutability": "view",
    "type": "function"
  },
  {
    "inputs": [
      { "internalType": "address", "name": "_profileid", "type": "address" }
    ],
    "name": "getFundsInThisRaffle",
    "outputs": [{ "internalType": "uint256", "name": "", "type": "uint256" }],
    "stateMutability": "view",
    "type": "function"
  },
  {
    "inputs": [],
    "name": "getGoal",
    "outputs": [{ "internalType": "uint256", "name": "", "type": "uint256" }],
    "stateMutability": "pure",
    "type": "function"
  },
  {
    "inputs": [],
    "name": "getLastWinnerAddress",
    "outputs": [{ "internalType": "address", "name": "", "type": "address" }],
    "stateMutability": "view",
    "type": "function"
  },
  {
    "inputs": [],
    "name": "getLastWinnerIndex",
    "outputs": [{ "internalType": "uint256", "name": "", "type": "uint256" }],
    "stateMutability": "view",
    "type": "function"
  },
  {
    "inputs": [
      { "internalType": "address", "name": "_profileid", "type": "address" }
    ],
    "name": "getNumberOfFollowers",
    "outputs": [{ "internalType": "uint256", "name": "", "type": "uint256" }],
    "stateMutability": "view",
    "type": "function"
  },
  {
    "inputs": [],
    "name": "getPool",
    "outputs": [{ "internalType": "address", "name": "", "type": "address" }],
    "stateMutability": "view",
    "type": "function"
  },
  {
    "inputs": [],
    "name": "getPriceFeed",
    "outputs": [{ "internalType": "uint256", "name": "", "type": "uint256" }],
    "stateMutability": "view",
    "type": "function"
  },
  {
    "inputs": [
      { "internalType": "uint256", "name": "profileId", "type": "uint256" }
    ],
    "name": "getProfileData",
    "outputs": [
      {
        "components": [
          { "internalType": "address", "name": "currency", "type": "address" },
          { "internalType": "uint256", "name": "amount", "type": "uint256" },
          { "internalType": "address", "name": "recipient", "type": "address" }
        ],
        "internalType": "struct ProfileData",
        "name": "",
        "type": "tuple"
      }
    ],
    "stateMutability": "view",
    "type": "function"
  },
  {
    "inputs": [
      { "internalType": "address", "name": "_profileid", "type": "address" }
    ],
    "name": "getProfileToRaffles",
    "outputs": [{ "internalType": "uint256", "name": "", "type": "uint256" }],
    "stateMutability": "view",
    "type": "function"
  },
  {
    "inputs": [
      { "internalType": "address", "name": "_profileid", "type": "address" }
    ],
    "name": "getProfileToWins",
    "outputs": [{ "internalType": "uint256", "name": "", "type": "uint256" }],
    "stateMutability": "view",
    "type": "function"
  },
  {
    "inputs": [
      { "internalType": "uint256", "name": "_requestId", "type": "uint256" }
    ],
    "name": "getRequestStatus",
    "outputs": [
      { "internalType": "bool", "name": "fulfilled", "type": "bool" },
      {
        "internalType": "uint256[]",
        "name": "randomWords",
        "type": "uint256[]"
      }
    ],
    "stateMutability": "view",
    "type": "function"
  },
  {
    "inputs": [
      { "internalType": "address", "name": "_profileid", "type": "address" }
    ],
    "name": "getTotalFundedProfile",
    "outputs": [{ "internalType": "uint256", "name": "", "type": "uint256" }],
    "stateMutability": "view",
    "type": "function"
  },
  {
    "inputs": [
      { "internalType": "address", "name": "_userAddress", "type": "address" }
    ],
    "name": "getUserAccountData",
    "outputs": [
      {
        "internalType": "uint256",
        "name": "totalCollateralBase",
        "type": "uint256"
      },
      { "internalType": "uint256", "name": "totalDebtBase", "type": "uint256" },
      {
        "internalType": "uint256",
        "name": "availableBorrowsBase",
        "type": "uint256"
      },
      {
        "internalType": "uint256",
        "name": "currentLiquidationThreshold",
        "type": "uint256"
      },
      { "internalType": "uint256", "name": "ltv", "type": "uint256" },
      { "internalType": "uint256", "name": "healthFactor", "type": "uint256" }
    ],
    "stateMutability": "view",
    "type": "function"
  },
  {
    "inputs": [],
    "name": "iWmatic",
    "outputs": [
      { "internalType": "contract IERC20", "name": "", "type": "address" }
    ],
    "stateMutability": "view",
    "type": "function"
  },
  {
    "inputs": [],
    "name": "iaWmatic",
    "outputs": [
      { "internalType": "contract IERC20", "name": "", "type": "address" }
    ],
    "stateMutability": "view",
    "type": "function"
  },
  {
    "inputs": [
      { "internalType": "uint256", "name": "profileId", "type": "uint256" },
      { "internalType": "bytes", "name": "data", "type": "bytes" }
    ],
    "name": "initializeFollowModule",
    "outputs": [{ "internalType": "bytes", "name": "", "type": "bytes" }],
    "stateMutability": "nonpayable",
    "type": "function"
  },
  {
    "inputs": [
      { "internalType": "uint256", "name": "profileId", "type": "uint256" },
      { "internalType": "address", "name": "follower", "type": "address" },
      {
        "internalType": "uint256",
        "name": "followNFTTokenId",
        "type": "uint256"
      }
    ],
    "name": "isFollowing",
    "outputs": [{ "internalType": "bool", "name": "", "type": "bool" }],
    "stateMutability": "view",
    "type": "function"
  },
  {
    "inputs": [],
    "name": "lastRequestId",
    "outputs": [{ "internalType": "uint256", "name": "", "type": "uint256" }],
    "stateMutability": "view",
    "type": "function"
  },
  {
    "inputs": [
      { "internalType": "address", "name": "follower", "type": "address" },
      { "internalType": "uint256", "name": "profileId", "type": "uint256" },
      { "internalType": "bytes", "name": "data", "type": "bytes" }
    ],
    "name": "processFollow",
    "outputs": [],
    "stateMutability": "nonpayable",
    "type": "function"
  },
  {
    "inputs": [
      { "internalType": "uint256", "name": "requestId", "type": "uint256" },
      {
        "internalType": "uint256[]",
        "name": "randomWords",
        "type": "uint256[]"
      }
    ],
    "name": "rawFulfillRandomWords",
    "outputs": [],
    "stateMutability": "nonpayable",
    "type": "function"
  },
  {
    "inputs": [{ "internalType": "uint256", "name": "", "type": "uint256" }],
    "name": "requestIds",
    "outputs": [{ "internalType": "uint256", "name": "", "type": "uint256" }],
    "stateMutability": "view",
    "type": "function"
  },
  {
    "inputs": [{ "internalType": "uint256", "name": "", "type": "uint256" }],
    "name": "s_requests",
    "outputs": [
      { "internalType": "bool", "name": "fulfilled", "type": "bool" },
      { "internalType": "bool", "name": "exists", "type": "bool" }
    ],
    "stateMutability": "view",
    "type": "function"
  },
  {
    "inputs": [],
    "name": "withdraw",
    "outputs": [],
    "stateMutability": "nonpayable",
    "type": "function"
  },
  { "stateMutability": "payable", "type": "receive" }
]
